metaspn_engine/__init__.py
metaspn_engine/core.py
metaspn_engine/engine.py
metaspn_engine/pipeline.py
metaspn_engine/podcast_game.py
metaspn_engine/protocols.py
metaspn_engine/transforms.py
metaspn_engine-0.0.1.dist-info/licenses/LICENSE
metaspn_engine-0.0.1.dist-info/METADATA
metaspn_engine-0.0.1.dist-info/WHEEL
metaspn_engine-0.0.1.dist-info/top_level.txt
metaspn_engine-0.0.1.dist-info/RECORD
