Metadata-Version: 2.4
Name: metaspn-engine
Version: 0.0.1
Summary: Minimal signal processing engine for observable games
Author-email: Leo Guinan <leo@metaspn.network>
License: MIT
Project-URL: Homepage, https://github.com/metaspn/metaspn-engine
Project-URL: Documentation, https://docs.metaspn.network/engine
Project-URL: Repository, https://github.com/metaspn/metaspn-engine
Project-URL: Bug Tracker, https://github.com/metaspn/metaspn-engine/issues
Keywords: signal-processing,game-engine,transformation,pipeline,metaspn
Classifier: Development Status :: 3 - Alpha
Classifier: Intended Audience :: Developers
Classifier: Topic :: Software Development :: Libraries :: Python Modules
Classifier: License :: OSI Approved :: MIT License
Classifier: Programming Language :: Python :: 3
Classifier: Programming Language :: Python :: 3.10
Classifier: Programming Language :: Python :: 3.11
Classifier: Programming Language :: Python :: 3.12
Classifier: Typing :: Typed
Requires-Python: >=3.10
License-File: LICENSE
Provides-Extra: dev
Requires-Dist: pytest>=7.0.0; extra == "dev"
Requires-Dist: pytest-cov>=4.0.0; extra == "dev"
Requires-Dist: mypy>=1.0.0; extra == "dev"
Requires-Dist: ruff>=0.1.0; extra == "dev"
Dynamic: license-file
